{
  "_fv": 47,
  "_type": "gui",
  "definition": {
    "type": 1,
    "width": 176,
    "height": 166,
    "inventoryOffsetX": 0,
    "inventoryOffsetY": 0,
    "renderBgLayer": true,
    "doesPauseGame": false,
    "components": [
      {
        "type": "inputslot",
        "data": {
          "inputLimit": {
            "value": "CUSTOM:ChaosCatalyst"
          },
          "disablePlacement": {
            "fixedValue": false
          },
          "color": {
            "value": -3355444,
            "falpha": 0.0
          },
          "id": 0,
          "disablePickup": {
            "fixedValue": true
          },
          "dropItemsWhenNotBound": false,
          "onSlotChanged": {
            "name": "Maybe"
          },
          "x": 204,
          "y": 73
        }
      },
      {
        "type": "label",
        "data": {
          "name": "label_insert_key",
          "text": {
            "fixedValue": "Insert Key"
          },
          "color": {
            "value": -256,
            "falpha": 0.0
          },
          "x": 189,
          "y": 41
        }
      },
      {
        "type": "label",
        "data": {
          "name": "label_to_access_the_dimension",
          "text": {
            "fixedValue": "To access the dimension"
          },
          "color": {
            "value": -256,
            "falpha": 0.0
          },
          "x": 156,
          "y": 53
        }
      }
    ],
    "gridSettings": {
      "sx": 18,
      "sy": 18,
      "ox": 11,
      "oy": 15,
      "snapOnGrid": false
    }
  }
}